toolbox_iop/__init__.py
toolbox_iop/json_check_tools.py
toolbox_iop/json_tools.py
toolbox_iop/logger_tools.py
toolbox_iop/print_tools.py
toolbox_iop/string_tools.py
toolbox_iop/cli/__init__.py
toolbox_iop/cli/check_cli.py
toolbox_iop/cli/count_cli.py
toolbox_iop/cli/print_cli.py
toolbox_iop-0.1.7.dist-info/METADATA
toolbox_iop-0.1.7.dist-info/WHEEL
toolbox_iop-0.1.7.dist-info/entry_points.txt
toolbox_iop-0.1.7.dist-info/RECORD
