Metadata-Version: 2.4
Name: toolbox-iop
Version: 0.1.7
Summary: The toolbox for json load save and print, you may find more function in the future.
Author-email: scorpion_free <scorpion_free@qq.com>
License: MIT
Requires-Python: >=3.7
Requires-Dist: json-repair>=0.25.3
Requires-Dist: rich>=10.11.0
Requires-Dist: tqdm>=4.64.1
Provides-Extra: dev
Requires-Dist: pytest>=7.0.0; extra == 'dev'
